dash_plate/__init__.py
dash_plate-0.1.0.dist-info/LICENSE
dash_plate-0.1.0.dist-info/METADATA
dash_plate-0.1.0.dist-info/WHEEL
dash_plate-0.1.0.dist-info/RECORD
