Metadata-Version: 2.3
Name: dash_plate
Version: 0.1.0
Summary: A small visualization library for creating dash-compatible  laboratory plate objects
Author: Griffin White
Author-email: griffin@gwc-solutions.ch
Requires-Python: >=3.10,<4.0
Classifier: Programming Language :: Python :: 3
Classifier: Programming Language :: Python :: 3.10
Classifier: Programming Language :: Python :: 3.11
Classifier: Programming Language :: Python :: 3.12
Classifier: Programming Language :: Python :: 3.13
